deskaone_bypass/__init__.py
deskaone_bypass/CloudFlare/__init__.py
deskaone_bypass/Database/__init__.py
deskaone_bypass/Exceptions/__init__.py
deskaone_bypass/Google/__init__.py
deskaone_bypass/Google/Android/__init__.py
deskaone_bypass/Google/Android/Key_Base64.py
deskaone_bypass/Google/Android/Response.py
deskaone_bypass/Google/Firebase/__init__.py
deskaone_bypass/Google/Firebase/Authentication.py
deskaone_bypass/Google/Firebase/AuthHTTPAdapter.py
deskaone_bypass/Google/Firebase/ClosableSSEClient.py
deskaone_bypass/Google/Firebase/Database.py
deskaone_bypass/Google/Firebase/Event.py
deskaone_bypass/Google/Firebase/Exceptions.py
deskaone_bypass/Google/Firebase/KeepAuthSession.py
deskaone_bypass/Google/Firebase/Pyre.py
deskaone_bypass/Google/Firebase/PyreResponse.py
deskaone_bypass/Google/Firebase/SSEClient.py
deskaone_bypass/Google/Firebase/SSLContext.py
deskaone_bypass/Google/Firebase/Storage.py
deskaone_bypass/Google/Firebase/Stream.py
deskaone_bypass/Google/identitytoolkit/__init__.py
deskaone_bypass/PyJWT/__init__.py
deskaone_bypass/PyJWT/algorithms.py
deskaone_bypass/PyJWT/api_jwk.py
deskaone_bypass/PyJWT/api_jws.py
deskaone_bypass/PyJWT/api_jwt.py
deskaone_bypass/PyJWT/exceptions.py
deskaone_bypass/PyJWT/help.py
deskaone_bypass/PyJWT/jwk_set_cache.py
deskaone_bypass/PyJWT/jwks_client.py
deskaone_bypass/PyJWT/py.typed
deskaone_bypass/PyJWT/types.py
deskaone_bypass/PyJWT/utils.py
deskaone_bypass/PyJWT/warnings.py
deskaone_bypass/Shortlink/__init__.py
deskaone_bypass-0.0.1rc24.dist-info/WHEEL
deskaone_bypass-0.0.1rc24.dist-info/METADATA
deskaone_bypass-0.0.1rc24.dist-info/RECORD
