Metadata-Version: 2.1
Name: deskaone-bypass
Version: 0.0.1rc24
Summary: 
Author: Antoni Oktha Fernandes
Author-email: 37358597+DesKaOne@users.noreply.github.com
Requires-Python: >=3.8,<4.0
Classifier: Programming Language :: Python :: 3
Classifier: Programming Language :: Python :: 3.8
Classifier: Programming Language :: Python :: 3.9
Classifier: Programming Language :: Python :: 3.10
Classifier: Programming Language :: Python :: 3.11
Requires-Dist: base58 (>=2.1.1,<3.0.0)
Requires-Dist: gcloud (>=0.18.3,<0.19.0)
Requires-Dist: google-api-python-client (>=2.97.0,<3.0.0)
Requires-Dist: google-auth-httplib2 (>=0.1.0,<0.2.0)
Requires-Dist: google-auth-oauthlib (>=1.0.0,<2.0.0)
Requires-Dist: jwt (>=1.3.1,<2.0.0)
Requires-Dist: oauth2client (>=4.1.3,<5.0.0)
Requires-Dist: psycopg2 (>=2.9.7,<3.0.0)
Requires-Dist: pycryptodome (>=3.18.0,<4.0.0)
Requires-Dist: pycryptodomex (>=3.18.0,<4.0.0)
Requires-Dist: python-dotenv (>=1.0.0,<2.0.0)
Requires-Dist: python-jwt (>=4.0.0,<5.0.0)
Requires-Dist: random-user-agent (>=1.0.1,<2.0.0)
Requires-Dist: requests[socks] (>=2.31.0,<3.0.0)
Requires-Dist: six (>=1.16.0,<2.0.0)
Requires-Dist: sqlalchemy (>=2.0.20,<3.0.0)
